snoringness/__init__.py
snoringness/snoringness.py
snoringness-0.0.0.dist-info/LICENSE
snoringness-0.0.0.dist-info/METADATA
snoringness-0.0.0.dist-info/WHEEL
snoringness-0.0.0.dist-info/top_level.txt
snoringness-0.0.0.dist-info/RECORD
