Metadata-Version: 2.1
Name: snoringness
Version: 0.0.0
Summary: Troll module made by pymoduledev.
Author: PyModuleDev
Author-email: pxcom@mail.com
Classifier: Development Status :: 5 - Production/Stable
Classifier: Intended Audience :: Developers
Classifier: License :: OSI Approved :: Apache Software License
Classifier: Programming Language :: Python :: 3
Requires-Python: >=3.6
License-File: LICENSE
